mmcls/__init__.py
mmcls/version.py
mmcls/.mim/model-index.yml
mmcls/.mim/configs/_base_/default_runtime.py
mmcls/.mim/configs/_base_/datasets/cifar100_bs16.py
mmcls/.mim/configs/_base_/datasets/cifar10_bs16.py
mmcls/.mim/configs/_base_/datasets/cub_bs8_384.py
mmcls/.mim/configs/_base_/datasets/cub_bs8_448.py
mmcls/.mim/configs/_base_/datasets/imagenet21k_bs128.py
mmcls/.mim/configs/_base_/datasets/imagenet_bs128_poolformer_medium_224.py
mmcls/.mim/configs/_base_/datasets/imagenet_bs128_poolformer_small_224.py
mmcls/.mim/configs/_base_/datasets/imagenet_bs256_rsb_a12.py
mmcls/.mim/configs/_base_/datasets/imagenet_bs256_rsb_a3.py
mmcls/.mim/configs/_base_/datasets/imagenet_bs32.py
mmcls/.mim/configs/_base_/datasets/imagenet_bs32_pil_bicubic.py
mmcls/.mim/configs/_base_/datasets/imagenet_bs32_pil_resize.py
mmcls/.mim/configs/_base_/datasets/imagenet_bs64.py
mmcls/.mim/configs/_base_/datasets/imagenet_bs64_autoaug.py
mmcls/.mim/configs/_base_/datasets/imagenet_bs64_convmixer_224.py
mmcls/.mim/configs/_base_/datasets/imagenet_bs64_mixer_224.py
mmcls/.mim/configs/_base_/datasets/imagenet_bs64_pil_resize.py
mmcls/.mim/configs/_base_/datasets/imagenet_bs64_pil_resize_autoaug.py
mmcls/.mim/configs/_base_/datasets/imagenet_bs64_swin_224.py
mmcls/.mim/configs/_base_/datasets/imagenet_bs64_swin_256.py
mmcls/.mim/configs/_base_/datasets/imagenet_bs64_swin_384.py
mmcls/.mim/configs/_base_/datasets/imagenet_bs64_t2t_224.py
mmcls/.mim/configs/_base_/datasets/stanford_cars_bs8_448.py
mmcls/.mim/configs/_base_/datasets/voc_bs16.py
mmcls/.mim/configs/_base_/datasets/pipelines/auto_aug.py
mmcls/.mim/configs/_base_/datasets/pipelines/rand_aug.py
mmcls/.mim/configs/_base_/models/efficientnet_b0.py
mmcls/.mim/configs/_base_/models/efficientnet_b1.py
mmcls/.mim/configs/_base_/models/efficientnet_b2.py
mmcls/.mim/configs/_base_/models/efficientnet_b3.py
mmcls/.mim/configs/_base_/models/efficientnet_b4.py
mmcls/.mim/configs/_base_/models/efficientnet_b5.py
mmcls-0.25.0.dist-info/LICENSE
mmcls-0.25.0.dist-info/METADATA
mmcls-0.25.0.dist-info/WHEEL
mmcls-0.25.0.dist-info/top_level.txt
mmcls-0.25.0.dist-info/RECORD
