Metadata-Version: 2.1
Name: mmcls
Version: 0.25.0
Summary: OpenMMLab Image Classification Toolbox and Benchmark
Home-page: https://github.com/open-mmlab/mmclassification
Author: MMClassification Contributors
Author-email: openmmlab@gmail.com
License: Apache License 2.0
Keywords: computer vision,image classification
Platform: UNKNOWN
Classifier: Development Status :: 4 - Beta
Classifier: License :: OSI Approved :: Apache Software License
Classifier: Operating System :: OS Independent
Classifier: Programming Language :: Python :: 3
Classifier: Programming Language :: Python :: 3.6
Classifier: Programming Language :: Python :: 3.7
Classifier: Programming Language :: Python :: 3.8
Classifier: Programming Language :: Python :: 3.9
Classifier: Topic :: Scientific/Engineering :: Artificial Intelligence
Requires-Dist: matplotlib (>=3.1.0)
Requires-Dist: numpy
Requires-Dist: packaging
Provides-Extra: all
Requires-Dist: albumentations (>=0.3.2) ; extra == 'all'
Requires-Dist: colorama ; extra == 'all'
Requires-Dist: requests ; extra == 'all'
Requires-Dist: rich ; extra == 'all'
Requires-Dist: scipy ; extra == 'all'
Requires-Dist: matplotlib (>=3.1.0) ; extra == 'all'
Requires-Dist: numpy ; extra == 'all'
Requires-Dist: packaging ; extra == 'all'
Requires-Dist: codecov ; extra == 'all'
Requires-Dist: flake8 ; extra == 'all'
Requires-Dist: interrogate ; extra == 'all'
Requires-Dist: isort (==4.3.21) ; extra == 'all'
Requires-Dist: mmdet ; extra == 'all'
Requires-Dist: pytest ; extra == 'all'
Requires-Dist: xdoctest (>=0.10.0) ; extra == 'all'
Requires-Dist: yapf ; extra == 'all'
Provides-Extra: mim
Requires-Dist: mmcv-full (<1.9.0,>=1.4.2) ; extra == 'mim'
Provides-Extra: optional
Requires-Dist: albumentations (>=0.3.2) ; extra == 'optional'
Requires-Dist: colorama ; extra == 'optional'
Requires-Dist: requests ; extra == 'optional'
Requires-Dist: rich ; extra == 'optional'
Requires-Dist: scipy ; extra == 'optional'
Provides-Extra: tests
Requires-Dist: codecov ; extra == 'tests'
Requires-Dist: flake8 ; extra == 'tests'
Requires-Dist: interrogate ; extra == 'tests'
Requires-Dist: isort (==4.3.21) ; extra == 'tests'
Requires-Dist: mmdet ; extra == 'tests'
Requires-Dist: pytest ; extra == 'tests'
Requires-Dist: xdoctest (>=0.10.0) ; extra == 'tests'
Requires-Dist: yapf ; extra == 'tests'
